setup.py
django_spreedly.egg-info/PKG-INFO
django_spreedly.egg-info/SOURCES.txt
django_spreedly.egg-info/dependency_links.txt
django_spreedly.egg-info/not-zip-safe
django_spreedly.egg-info/requires.txt
django_spreedly.egg-info/top_level.txt
spreedly/__init__.py
spreedly/admin.py
spreedly/forms.py
spreedly/middleware.py
spreedly/models.py
spreedly/settings.py
spreedly/signals.py
spreedly/urls.py
spreedly/views.py
spreedly/migrations/0001_initial.py
spreedly/migrations/0002_rename_fields_plan_force_renew__duration__spreedly_id.py
spreedly/migrations/0003_auto__chg_field_plan_description.py
spreedly/migrations/0004_auto__add_field_subscription_plan__add_field_subscription_url.py
spreedly/migrations/0005_rename__trial_elegible.py
spreedly/migrations/0006_auto__chg_field_subscription_plan.py
spreedly/migrations/0007_auto__add_feegroup__add_fee__add_lineitem.py
spreedly/migrations/0008_auto__add_field_lineitem_started__add_field_lineitem_reference__add_fi.py
spreedly/migrations/0009_auto__add_field_subscription_store_credit.py
spreedly/migrations/0010_auto__del_gift__chg_field_subscription_plan.py
spreedly/migrations/__init__.py
spreedly/templatetags/__init__.py
spreedly/tests/__init__.py
spreedly/tests/helpers.py
spreedly/tests/mocks.py
spreedly/tests/test_views.py
spreedly/tests/unit_tests.py