Metadata-Version: 1.1
Name: django-spreedly
Version: 2.0.9
Summary: django-spreedly integrates support for the spreedly subscription service
Home-page: www.github.com/mediapop/django-spreedly
Author: James Rivett-Carnac
Author-email: dev@mediapop.co
License: UNKNOWN
Platform: UNKNOWN
Classifier: Intended Audience :: Developers
Classifier: Intended Audience :: System Administrators
Classifier: Operating System :: OS Independent
Classifier: Programming Language :: Python
Classifier: License :: OSI Approved :: MIT License
Classifier: Topic :: Software Development :: Libraries :: Python Modules
Classifier: Framework :: Django
